bspc/__init__.py
bspc/classes.py
bspc/query.py
bspcpy-1.0.3.3.dist-info/METADATA
bspcpy-1.0.3.3.dist-info/WHEEL
bspcpy-1.0.3.3.dist-info/licenses/LICENSE
bspcpy-1.0.3.3.dist-info/RECORD
