Metadata-Version: 2.1
Name: bspcpy
Version: 1.0.3.3
Summary: bspc wrapper for python
Keywords: python bspwm bspc
Author-Email: AlanJS26 <alanjoses.29@gmail.com>
License: MIT
Project-URL: Homepage, https://github.com/AlanJs26/bspcpy
Requires-Python: >=3.10
